markdown_frames/__init__.py
markdown_frames/pandas_dataframe.py
markdown_frames/spark_dataframe.py
markdown_frames/table.py
markdown_frames/type_definitions.py
markdown_frames/utils.py
markdown_frames-1.0.6.dist-info/LICENSE
markdown_frames-1.0.6.dist-info/METADATA
markdown_frames-1.0.6.dist-info/WHEEL
markdown_frames-1.0.6.dist-info/top_level.txt
markdown_frames-1.0.6.dist-info/RECORD
