Metadata-Version: 2.1
Name: markdown-frames
Version: 1.0.6
Summary: Markdown tables parsing to pyspark / pandas DataFrames
Home-page: https://github.com/exacaster/markdown_frames
Author: Exacaster
Author-email: support@exacaster.com
Classifier: Programming Language :: Python :: 3
Classifier: License :: OSI Approved :: MIT License
Classifier: Operating System :: OS Independent
Classifier: Topic :: Software Development :: Testing
License-File: LICENSE
Provides-Extra: pandas
Requires-Dist: pandas ; extra == 'pandas'
Provides-Extra: pyspark
Requires-Dist: pyspark ; extra == 'pyspark'
